setup.py
dfvc/__init__.py
dfvc/tools.py
dfvc.egg-info/PKG-INFO
dfvc.egg-info/SOURCES.txt
dfvc.egg-info/dependency_links.txt
dfvc.egg-info/requires.txt
dfvc.egg-info/top_level.txt