Metadata-Version: 2.1
Name: dfvc
Version: 0.0.3
Summary: Data Frame Version Control
Author: Leonardo Cardillo
Requires-Dist: pandas
Requires-Dist: tzlocal
